odoo8_addon_base_multi_image-8.0.2.0.1-nspkg.pth
odoo_addons/base_multi_image/README.rst
odoo_addons/base_multi_image/__init__.py
odoo_addons/base_multi_image/__openerp__.py
odoo_addons/base_multi_image/hooks.py
odoo_addons/base_multi_image/i18n/am.po
odoo_addons/base_multi_image/i18n/ar.po
odoo_addons/base_multi_image/i18n/base_multi_image.pot
odoo_addons/base_multi_image/i18n/bg.po
odoo_addons/base_multi_image/i18n/bs.po
odoo_addons/base_multi_image/i18n/ca.po
odoo_addons/base_multi_image/i18n/ca_ES.po
odoo_addons/base_multi_image/i18n/cs.po
odoo_addons/base_multi_image/i18n/da.po
odoo_addons/base_multi_image/i18n/da_DK.po
odoo_addons/base_multi_image/i18n/de.po
odoo_addons/base_multi_image/i18n/el_GR.po
odoo_addons/base_multi_image/i18n/en_GB.po
odoo_addons/base_multi_image/i18n/es.po
odoo_addons/base_multi_image/i18n/es_AR.po
odoo_addons/base_multi_image/i18n/es_CL.po
odoo_addons/base_multi_image/i18n/es_CO.po
odoo_addons/base_multi_image/i18n/es_CR.po
odoo_addons/base_multi_image/i18n/es_DO.po
odoo_addons/base_multi_image/i18n/es_EC.po
odoo_addons/base_multi_image/i18n/es_ES.po
odoo_addons/base_multi_image/i18n/es_MX.po
odoo_addons/base_multi_image/i18n/es_PE.po
odoo_addons/base_multi_image/i18n/es_PY.po
odoo_addons/base_multi_image/i18n/es_VE.po
odoo_addons/base_multi_image/i18n/et.po
odoo_addons/base_multi_image/i18n/eu.po
odoo_addons/base_multi_image/i18n/fa.po
odoo_addons/base_multi_image/i18n/fi.po
odoo_addons/base_multi_image/i18n/fr.po
odoo_addons/base_multi_image/i18n/fr_CA.po
odoo_addons/base_multi_image/i18n/fr_CH.po
odoo_addons/base_multi_image/i18n/gl.po
odoo_addons/base_multi_image/i18n/gl_ES.po
odoo_addons/base_multi_image/i18n/he.po
odoo_addons/base_multi_image/i18n/hr.po
odoo_addons/base_multi_image/i18n/hr_HR.po
odoo_addons/base_multi_image/i18n/hu.po
odoo_addons/base_multi_image/i18n/id.po
odoo_addons/base_multi_image/i18n/it.po
odoo_addons/base_multi_image/i18n/ja.po
odoo_addons/base_multi_image/i18n/ko.po
odoo8_addon_base_multi_image-8.0.2.0.1.dist-info/METADATA
odoo8_addon_base_multi_image-8.0.2.0.1.dist-info/WHEEL
odoo8_addon_base_multi_image-8.0.2.0.1.dist-info/namespace_packages.txt
odoo8_addon_base_multi_image-8.0.2.0.1.dist-info/top_level.txt
odoo8_addon_base_multi_image-8.0.2.0.1.dist-info/RECORD
